aissemble_messaging/__init__.py
aissemble_messaging/ack_strategy.py
aissemble_messaging/exception/base_messaging_error.py
aissemble_messaging/exception/process_message_error.py
aissemble_messaging/exception/topic_not_supported_error.py
aissemble_messaging/future.py
aissemble_messaging/message.py
aissemble_messaging/messaging_client.py
aissemble_messaging/service_resources/classpath/angus-activation-2.0.2.jar
aissemble_messaging/service_resources/classpath/aopalliance-1.0.jar
aissemble_messaging/service_resources/classpath/asm-9.7.jar
aissemble_messaging/service_resources/classpath/baton-maven-plugin-1.1.2.jar
aissemble_messaging/service_resources/classpath/byte-buddy-1.15.1.jar
aissemble_messaging/service_resources/classpath/checker-qual-3.43.0.jar
aissemble_messaging/service_resources/classpath/commons-collections4-4.4.jar
aissemble_messaging/service_resources/classpath/commons-configuration2-2.11.0.jar
aissemble_messaging/service_resources/classpath/commons-io-2.16.1.jar
aissemble_messaging/service_resources/classpath/commons-lang3-3.18.0.jar
aissemble_messaging/service_resources/classpath/commons-text-1.13.0.jar
aissemble_messaging/service_resources/classpath/cucumber-reporting-5.9.0.jar
aissemble_messaging/service_resources/classpath/error_prone_annotations-2.27.0.jar
aissemble_messaging/service_resources/classpath/failureaccess-1.0.2.jar
aissemble_messaging/service_resources/classpath/fermenter-mda-2.10.5.jar
aissemble_messaging/service_resources/classpath/foundation-core-java-2.0.0.jar
aissemble_messaging/service_resources/classpath/foundation-messaging-java-2.0.0.jar
aissemble_messaging/service_resources/classpath/foundation-messaging-python-service-2.0.0.jar
aissemble_messaging/service_resources/classpath/gson-2.11.0.jar
aissemble_messaging/service_resources/classpath/guava-33.4.0-jre.jar
aissemble_messaging/service_resources/classpath/guice-7.0.0.jar
aissemble_messaging/service_resources/classpath/guice-assistedinject-7.0.0.jar
aissemble_foundation_messaging_python-2.0.0.dist-info/LICENSE
aissemble_foundation_messaging_python-2.0.0.dist-info/LICENSE.txt
aissemble_foundation_messaging_python-2.0.0.dist-info/METADATA
aissemble_foundation_messaging_python-2.0.0.dist-info/WHEEL
aissemble_foundation_messaging_python-2.0.0.dist-info/RECORD
