Metadata-Version: 2.3
Name: aissemble-foundation-messaging-python
Version: 2.0.0
Summary: Defines a root level messaging architecture in python
License: Apache-2.0
Author: aiSSEMBLE Baseline Community
Author-email: aissemble@bah.com
Requires-Python: >=3.9
Classifier: License :: OSI Approved :: Apache Software License
Classifier: Programming Language :: Python :: 3
Classifier: Programming Language :: Python :: 3.9
Classifier: Programming Language :: Python :: 3.10
Classifier: Programming Language :: Python :: 3.11
Classifier: Programming Language :: Python :: 3.12
Classifier: Programming Language :: Python :: 3.13
Requires-Dist: krausening (>=21)
Requires-Dist: py4j (==0.10.9.7)
Project-URL: Documentation, https://boozallen.github.io/aissemble
Project-URL: Homepage, https://github.com/boozallen/aissemble
Project-URL: Repository, https://github.com/boozallen/aissemble
